pinboard_to_sqlite/__init__.py
pinboard_to_sqlite/cli.py
pinboard_to_sqlite-1.2.0.dist-info/entry_points.txt
pinboard_to_sqlite-1.2.0.dist-info/LICENSE
pinboard_to_sqlite-1.2.0.dist-info/WHEEL
pinboard_to_sqlite-1.2.0.dist-info/METADATA
pinboard_to_sqlite-1.2.0.dist-info/RECORD
