Metadata-Version: 2.1
Name: pinboard-to-sqlite
Version: 1.2.0
Summary: Save data from Pinboard to a SQLite database
Home-page: https://github.com/jacobian/pinboard-to-sqlite/
License: WTFPL
Author: Jacob Kaplan-Moss
Author-email: jacob@jacobian.org
Requires-Python: >=3.6,<4.0
Classifier: License :: Other/Proprietary License
Classifier: Programming Language :: Python :: 3
Classifier: Programming Language :: Python :: 3.6
Classifier: Programming Language :: Python :: 3.7
Classifier: Programming Language :: Python :: 3.8
Requires-Dist: click (>=7.0,<8.0)
Requires-Dist: python-dateutil (>=2.8.1,<3.0.0)
Requires-Dist: requests (>=2.22.0,<3.0.0)
Requires-Dist: sqlite-utils (>=1.12.1,<2.0.0)
Project-URL: Repository, https://github.com/jacobian/pinboard-to-sqlite/
